{
  "zh_news": {
    "頭條新聞": [
      {
        "title": "政院：立院侵害新聞自由悖離憲政 將尋合法合憲救濟",
        "link": "https://www.cna.com.tw/news/aipl/202601300358.aspx",
        "source": "中央社",
        "published": "2026-01-30T07:31:51+00:00",
        "summary": "行政院於30日發表聲明，對立法院通過的多項修正法案表示關切，這些法案包括「衛星廣播電視法」、「政黨及其附隨組織不當取得財產處理條例」及「立法院組織法」。行政院指出，立法院在未審議中央政府總預算案的情況..."
      },
      {
        "title": "民進黨：立院11屆第4會期創總預算一毛未審荒謬紀錄",
        "link": "https://www.cna.com.tw/news/aipl/202601300356.aspx",
        "source": "中央社",
        "published": "2026-01-30T07:21:47+00:00",
        "summary": "民進黨發言人李坤城於30日表示，立法院第11屆第4會期的最後一天，藍白聯手通過多項爭議法案，導致立法權凌駕於司法獨立審判之上。李坤城指出，此次會期創下總預算一毛未審的紀錄，這被視為嚴重失職，並對選民的..."
      },
      {
        "title": "立院付委民眾黨版國防預算條例 總統：再次侵犯行政權",
        "link": "https://www.cna.com.tw/news/aipl/202601300352.aspx",
        "source": "中央社",
        "published": "2026-01-30T06:53:36+00:00",
        "summary": "國造潛艦原型艦海鯤號於29日完成首次潛航測試，達成進度目標。總統賴清德表示，此次測試標誌著台灣國防自主的歷史時刻，並強調台灣成為全球少數能自製潛艦的國家之一。然而，立法院近日將民眾黨版國防特別預算條例..."
      },
      {
        "title": "立院會期結束 韓國瑜籲朝野用對話取代對抗",
        "link": "https://www.cna.com.tw/news/aipl/202601300349.aspx",
        "source": "中央社",
        "published": "2026-01-30T06:13:29+00:00",
        "summary": "立法院本會期於30日結束，立法院長韓國瑜在最後一次院會上發表談話。他指出，在第4會期內，全體立委共同努力通過了多項議案，但仍有部分議案因朝野立場不同而未能達成共識。韓國瑜呼籲朝野應以對話取代對抗，強調..."
      },
      {
        "title": "國防部：裝備延壽及維修需要4.5兆元並非事實",
        "link": "https://www.cna.com.tw/news/aipl/202601300348.aspx",
        "source": "中央社",
        "published": "2026-01-30T06:13:27+00:00",
        "summary": "國防部於30日表示，針對「強化防衛韌性及不對稱戰力計畫採購特別條例」的預算問題，澄清所需的1兆2500億元預算為上限，並非外界所傳的4.5兆元。國防部指出，該計畫將在8年內執行，所獲得的新式武器裝備將..."
      },
      {
        "title": "美參院外委會通過4法案 4月川習會前凸顯美台夥伴關係",
        "link": "https://www.cna.com.tw/news/aipl/202601300344.aspx",
        "source": "中央社",
        "published": "2026-01-30T05:58:18+00:00",
        "summary": "美國聯邦參議院外交委員會於29日通過四項針對台灣的法案，旨在增強台灣的能源安全、通訊韌性及外交影響力。這一舉措正值美國總統川普預計於4月訪問中國之際，顯示出美國國會成員在對抗北京方面的積極行動。這些法..."
      },
      {
        "title": "立院三讀 必要藥品定期申報庫存供需避免斷藥",
        "link": "https://www.cna.com.tw/news/aipl/202601300342.aspx",
        "source": "中央社",
        "published": "2026-01-30T05:57:14+00:00",
        "summary": "立法院於30日三讀通過修正藥事法及藥害救濟法部分條文，旨在強化缺藥預警與應變機制，以避免斷藥情形再度發生。根據新規定，持有必要藥品許可證的藥商需定期向衛生福利部申報藥品的製造、輸入及供應情況。若藥商未..."
      },
      {
        "title": "立院組織法修正三讀 公費助理工資變立委補助費",
        "link": "https://www.cna.com.tw/news/aipl/202601300341.aspx",
        "source": "中央社",
        "published": "2026-01-30T05:37:09+00:00",
        "summary": "立法院於30日進行會議，三讀修正通過立法院組織法部分條文，明確規定每年應以公務預算編列立法委員的補助費用。該補助費用項目包括立委辦公事務費、公費助理工資、專業加給及資深加給等。此次修正的條文將於立法院..."
      }
    ],
    "產經": [
      {
        "title": "瀚荃公開收購全宇昕15%股權 每股104元溢價逾2成",
        "link": "https://www.cna.com.tw/news/afe/202601300350.aspx",
        "source": "中央社",
        "published": "2026-01-30T06:18:31+00:00",
        "summary": "瀚荃於30日召開董事會，決議公開收購全宇昕15%的股權，涉及已發行股份3460萬1541股中的519萬1000股。此次公開收購的期間定為2024年2月3日至3月10日，收購價格為每股104元。根據市場..."
      },
      {
        "title": "今彩539第115026期頭獎1注中獎",
        "link": "https://www.cna.com.tw/news/ahel/202601300347.aspx",
        "source": "中央社",
        "published": "2026-01-30T06:09:24+00:00",
        "summary": "今彩539第115026期於30日開獎，開獎號碼為16、29、36、30、17。此次開獎中，頭獎共產生1注中獎，獎金為新台幣800萬元。"
      },
      {
        "title": "大樂透第115009期頭獎槓龜",
        "link": "https://www.cna.com.tw/news/ahel/202601300346.aspx",
        "source": "中央社",
        "published": "2026-01-30T06:05:22+00:00",
        "summary": "大樂透第115009期於30日晚間開獎，開獎號碼為32、39、13、31、09、27，特別號為19。根據派彩結果，本期頭獎及貳獎均未中出，造成槓龜情況。此結果意味著，參與者在本期未能獲得頭獎或貳獎的獎..."
      },
      {
        "title": "景碩未來3年資本支出估235億元 擴ABF產能設備",
        "link": "https://www.cna.com.tw/news/afe/202601300336.aspx",
        "source": "中央社",
        "published": "2026-01-30T05:11:56+00:00",
        "summary": "IC載板廠景碩於30日公告，董事會已核准新增專案資本支出預算，預估規模約新台幣235億元。該資本支出主要用於未來三年內擴充ABF產能設備的需求。此外，董事會同時通過擬配發現金股利，每股1.75元。此舉..."
      },
      {
        "title": "大樂透第115009期開獎",
        "link": "https://www.cna.com.tw/news/ahel/202601300331.aspx",
        "source": "中央社",
        "published": "2026-01-30T04:50:45+00:00",
        "summary": "大樂透第115009期於30日晚間開獎，開獎號碼為32、39、13、31、09、27，特別號為19。此次開獎吸引了眾多彩迷的關注，相關的中獎資訊及獎金分配將在後續公布。"
      },
      {
        "title": "回應美智庫 央行反駁：壽險匯率會計新制無關匯率政策",
        "link": "https://www.cna.com.tw/news/afe/202601300330.aspx",
        "source": "中央社",
        "published": "2026-01-30T04:47:43+00:00",
        "summary": "中央銀行於30日回應美國智庫學者對台灣壽險業匯率會計新制的質疑，強調該新制屬於金融監理委員會的權責範疇，與央行的匯率政策無關。央行指出，其主要任務是維持新台幣匯率的雙向動態穩定，並明言不會設立新台幣升..."
      },
      {
        "title": "今彩539第115026期開獎",
        "link": "https://www.cna.com.tw/news/ahel/202601300329.aspx",
        "source": "中央社",
        "published": "2026-01-30T04:43:41+00:00",
        "summary": "今彩539第115026期於30日開獎，開獎號碼為16、29、36、30、17。此次開獎中，3星彩的中獎號碼為900，4星彩的中獎號碼為1224。"
      },
      {
        "title": "集邦：Meta零件訂單上修 今年全球AR眼鏡出貨年增53%",
        "link": "https://www.cna.com.tw/news/afe/202601300319.aspx",
        "source": "中央社",
        "published": "2026-01-30T04:06:19+00:00",
        "summary": "根據研調機構集邦科技的最新報告，隨著人工智慧與穿戴式裝置的深度融合，Meta的Ray-Ban Display Glasses在市場反應上超出預期，導致其關鍵零組件訂單在近半年內大幅上修。報告指出，隨著..."
      }
    ],
    "全球國際新聞": [
      {
        "title": "西班牙警方逮捕中籍髮廊老闆 涉透過加密貨幣資助哈瑪斯",
        "link": "https://www.cna.com.tw/news/aopl/202601300357.aspx",
        "source": "中央社",
        "published": "2026-01-30T07:29:49+00:00",
        "summary": "西班牙警方於30日逮捕一名38歲中國籍男子，該男子在巴塞隆納附近經營髮廊。警方表示，此人涉嫌透過轉帳約60萬歐元的加密貨幣，資助巴勒斯坦武裝組織哈瑪斯。該事件引發了當地及國際社會的關注，警方正在進一步..."
      },
      {
        "title": "CNN前主播勒蒙現身反移民執法示威 被控違法而遭逮捕",
        "link": "https://www.cna.com.tw/news/aopl/202601300354.aspx",
        "source": "中央社",
        "published": "2026-01-30T07:05:42+00:00",
        "summary": "美國有線電視新聞網前主播勒蒙因報導明尼蘇達州明尼阿波利斯的反移民執法示威活動而遭逮捕。根據其律師的說法，勒蒙目前為獨立記者，參與了抗議政府對移民進行大規模打壓的活動。此次示威活動引發了廣泛關注，勒蒙的..."
      },
      {
        "title": "中國應急管理部長臨時缺席會議 傳被帶走調查",
        "link": "https://www.cna.com.tw/news/acn/202601300353.aspx",
        "source": "中央社",
        "published": "2026-01-30T06:53:38+00:00",
        "summary": "中國應急管理部部長王祥喜於29日臨時缺席央企安全生產工作視訊會議，引發社群對其被帶走調查的猜測。王祥喜在27日的應急管理部民主生活會上強調了堅守廉潔底線的重要性，並表示要在此方面帶好頭。此事件引起廣泛..."
      },
      {
        "title": "施凱爾：中國同意解除對7名英國國會議員制裁",
        "link": "https://www.cna.com.tw/news/aopl/202601300345.aspx",
        "source": "中央社",
        "published": "2026-01-30T06:01:20+00:00",
        "summary": "英國首相施凱爾於30日表示，中國已同意解除對7名英國國會議員的制裁，包括5名下議院議員及2名上議院議員。這些議員因批評北京侵犯維吾爾少數民族人權而於2021年遭到禁止入境中國。施凱爾的聲明標誌著中英兩..."
      },
      {
        "title": "聯準會前鷹派官員華許獲提名接主席 降息立場轉與川普一致",
        "link": "https://www.cna.com.tw/news/aopl/202601300343.aspx",
        "source": "中央社",
        "published": "2026-01-30T05:58:16+00:00",
        "summary": "前美國聯邦準備理事會官員華許獲川普總統提名擔任下一任Fed主席。華許曾被視為通膨政策的「鷹派」，但目前已轉變立場，支持川普團隊主張的大幅降息。此提名引發市場關注，因華許的政策取向可能影響未來的貨幣政策..."
      },
      {
        "title": "川普提名聯準會新主席人選 市場擔憂緩解避險資產金銀大跌",
        "link": "https://www.cna.com.tw/news/aopl/202601300338.aspx",
        "source": "中央社",
        "published": "2026-01-30T05:15:00+00:00",
        "summary": "美國總統川普於30日宣布提名金融家華許擔任下任聯邦準備理事會主席，此舉緩解了市場對於貨幣政策的不確定性。隨著投資者情緒改善，避險資產黃金與白銀價格大幅下跌，分別跌至每盎司約1,800美元和23美元的低..."
      },
      {
        "title": "泰國大選 民調：代表年輕世代人民黨維持領先",
        "link": "https://www.cna.com.tw/news/aopl/202601300332.aspx",
        "source": "中央社",
        "published": "2026-01-30T04:54:47+00:00",
        "summary": "泰國將於2月8日舉行大選，最新民調顯示，代表年輕世代及改革派的人民黨持續受到選民支持。該黨總理候選人納塔彭的支持率為29.08%，位居民調首位。現任總理、泰自豪黨的總理候選人阿努廷則以22.24%的支..."
      },
      {
        "title": "聯合國：緬甸大選期間 至少170平民死於軍事空襲",
        "link": "https://www.cna.com.tw/news/aopl/202601300328.aspx",
        "source": "中央社",
        "published": "2026-01-30T04:43:39+00:00",
        "summary": "聯合國人權事務高級專員公署（OHCHR）報告指出，在2025年12月至2026年1月的緬甸大選期間，至少有170名平民因軍事空襲而喪生。該報告強調，這些事件反映出當地持續的暴力情勢，並對平民安全構成嚴..."
      }
    ],
    "社會": [
      {
        "title": "童子瑋提三節敬老金加倍政見 年領1.8萬元",
        "link": "https://www.cna.com.tw/news/aloc/202601300359.aspx",
        "source": "中央社",
        "published": "2026-01-30T07:46:54+00:00",
        "summary": "民進黨基隆市長提名人童子瑋於30日表示，若當選市長，將把農曆春節、端午節及中秋節的敬老金從新台幣3000元加倍至6000元，年總額將達1萬8000元。此政策旨在提升對長者的關懷與支持，並強調對基隆市老..."
      },
      {
        "title": "替代役男遭丟包輾斃 友人：案發前1小時仍清醒對話",
        "link": "https://www.cna.com.tw/news/asoc/202601300351.aspx",
        "source": "中央社",
        "published": "2026-01-30T06:25:33+00:00",
        "summary": "溫姓男子在新北市遭計程車司機丟包後被輾斃。根據其友人提供的資訊，溫男在案發前1小時仍能進行語音訊息聊天，顯示他當時處於清醒狀態。友人對於溫男在車上未發出聲音感到疑惑，並希望能釐清事件的真相。此事件引發..."
      },
      {
        "title": "新北慈濟醫院廁所遭縱火已撲滅 嫌犯送辦",
        "link": "https://www.cna.com.tw/news/asoc/202601300340.aspx",
        "source": "中央社",
        "published": "2026-01-30T05:35:07+00:00",
        "summary": "新北市新店區慈濟醫院急診室廁所於30日晚間發生縱火事件，所幸醫院保全迅速撲滅火勢，未造成人員傷亡。警方調閱監視器後，確認嫌犯為一名男性病患，並將依公共危險罪嫌函請台北地檢署進行偵辦。此事件引起當地警方..."
      },
      {
        "title": "北市樂活夜櫻季開跑 估2/9進入最佳賞花期",
        "link": "https://www.cna.com.tw/news/aloc/202601300339.aspx",
        "source": "中央社",
        "published": "2026-01-30T05:24:05+00:00",
        "summary": "台北市樂活夜櫻季於今日正式開展。根據公園處的報告，目前夜櫻花開約20%。預計最佳觀賞期將於2月9日至13日之間到來。為了提升觀賞體驗，活動將搭配特別設計的燈光照明，旨在為民眾呈現層次豐富的視覺盛宴。"
      },
      {
        "title": "膠帶封口鼻致死 台南2男分別遭判13年7月、12年",
        "link": "https://www.cna.com.tw/news/asoc/202601300335.aspx",
        "source": "中央社",
        "published": "2026-01-30T05:03:54+00:00",
        "summary": "台南市一名呂姓男子於113年10月因金錢糾紛與他人談判時遭到毆打，並被用膠帶綑綁四肢及口鼻，最終被棄置於堤防處窒息死亡。台南地方法院於近日對此案件作出判決，分別對涉案的詹姓及謝姓兩名男子判處13年7個..."
      },
      {
        "title": "苗縣遭丟埋禽流感死雞案 業者、地主交保限制出境",
        "link": "https://www.cna.com.tw/news/asoc/202601300325.aspx",
        "source": "中央社",
        "published": "2026-01-30T04:37:32+00:00",
        "summary": "台中市豐康畜牧場因隱匿禽流感疫情，將逾千隻死雞埋於苗栗縣後龍鎮的私有地。苗栗地檢署於30日對雲姓牧場業者及顏姓地主進行訊問，並依據廢棄物清理法對兩人分別處以40萬元及20萬元的交保金，同時限制其出境與..."
      },
      {
        "title": "平溪天燈節2/27首登場 3盞20呎福馬主燈搶亮相",
        "link": "https://www.cna.com.tw/news/aloc/202601300317.aspx",
        "source": "中央社",
        "published": "2026-01-30T04:05:15+00:00",
        "summary": "2026新北市平溪天燈節將於2月27日在平溪國中舉行，並於3月3日移至十分廣場，整個活動將施放9波天燈。此次活動的主燈為三盞高達20呎的福馬主燈，旨在吸引民眾參與。極地超馬運動員陳彥博擔任活動代言人，..."
      },
      {
        "title": "豐康牧場隱匿禽流感疫情 中市203養禽場無異狀",
        "link": "https://www.cna.com.tw/news/aloc/202601300314.aspx",
        "source": "中央社",
        "published": "2026-01-30T03:54:08+00:00",
        "summary": "台中市豐原區的豐康牧場被指隱匿禽流感疫情。根據市政府的調查，苗栗的一名顏姓地主自今年1月起被委託運送死雞至該牧場進行掩埋。市府對203個養禽場進行訪視，結果顯示這些場域均無異常情況，且目前市售的蛋品也..."
      }
    ],
    "生活": [
      {
        "title": "機師離職台灣虎航取消1%航班 民航局促維護旅客權益",
        "link": "https://www.cna.com.tw/news/ahel/202601300333.aspx",
        "source": "中央社",
        "published": "2026-01-30T05:00:49+00:00",
        "summary": "台灣虎航因近期機師離職，取消約1%的航班，主要影響日本夏季航班，取消時間集中在3至5月。民航局已要求台灣虎航妥善處理取消航班的相關事宜，以維護旅客權益。該局強調，航空公司應確保乘客獲得適當的通知及補償..."
      },
      {
        "title": "乘客遭丟包輾斃 學者籲叫車平台納運輸安全監理",
        "link": "https://www.cna.com.tw/news/ahel/202601300326.aspx",
        "source": "中央社",
        "published": "2026-01-30T04:37:34+00:00",
        "summary": "溫姓男子在接受多元計程車服務後遭到司機丟包，最終被輾斃。事件引發學者關注，呼籲叫車平台應納入運輸安全監理體系，並賦予相關監理責任。此外，學者建議車隊及車行需加強對駕駛的教育訓練，以防止駕駛因情緒失控或..."
      },
      {
        "title": "紙風車368工程「椅子會」小額募款 陳其邁響應",
        "link": "https://www.cna.com.tw/news/acul/202601300313.aspx",
        "source": "中央社",
        "published": "2026-01-30T03:51:06+00:00",
        "summary": "紙風車「368鄉鎮市區兒童藝術工程」近日啟動「椅子會」小額募款行動，旨在支持兒童藝術發展。高雄市長陳其邁表示全力支持此項計畫，並捐出100本親筆簽名的書籍《青年的四個大夢》以助募款。他強調「孩子的椅子..."
      },
      {
        "title": "115年首例染漢他病毒亡 北市7旬翁發病8天過世",
        "link": "https://www.cna.com.tw/news/ahel/202601300307.aspx",
        "source": "中央社",
        "published": "2026-01-30T03:27:53+00:00",
        "summary": "疾管署於30日公布國內今年首例染漢他病毒死亡案例，受害者為一名70多歲的男性，具慢性病史。該名男子於1月上旬出現咳嗽及喘息等症狀，經過約8天後不幸過世。調查顯示，住家附近捕獲的4隻老鼠中，有2隻的檢測..."
      },
      {
        "title": "無照駕駛加重罰則31日實施 違規者需自費參加講習",
        "link": "https://www.cna.com.tw/news/ahel/202601300303.aspx",
        "source": "中央社",
        "published": "2026-01-30T03:14:44+00:00",
        "summary": "立法院日前三讀通過道路交通管理處罰條例修法，將於31日正式實施，針對無照駕駛的罰鍰進行調整。根據新規定，無照駕駛機車的最高罰鍰為3萬6000元，汽車則為6萬元。此外，所有無照駕駛的違規者必須自費參加交..."
      },
      {
        "title": "日本SPOGOMI撿垃圾運動賽事 彭啓明盼組台灣隊",
        "link": "https://www.cna.com.tw/news/ahel/202601300297.aspx",
        "source": "中央社",
        "published": "2026-01-30T03:01:31+00:00",
        "summary": "日本SPOGOMI聯盟推動的撿垃圾運動賽事近年來受到國際關注。環境部長彭啓明於30日表示，該活動結合趣味競賽與環境保護的核心價值，並計畫組建台灣代表隊，期望未來能參加SPOGOMI世界盃。此舉旨在提升..."
      },
      {
        "title": "台鐵平溪線31日復駛 公路接駁同步停止",
        "link": "https://www.cna.com.tw/news/ahel/202601300294.aspx",
        "source": "中央社",
        "published": "2026-01-30T02:57:25+00:00",
        "summary": "台鐵公司宣布，平溪線瑞芳至菁桐間的列車將於2024年1月31日恢復正常運行。該線路在停駛期間提供的瑞芳至菁桐公路接駁服務將同時停止。此次恢復行駛標誌著平溪線的正常運作回歸，為乘客提供更便捷的交通選擇。"
      },
      {
        "title": "嘉義8旬翁排尿困難 手術取出24顆膀胱結石",
        "link": "https://www.cna.com.tw/news/ahel/202601300279.aspx",
        "source": "中央社",
        "published": "2026-01-30T02:23:53+00:00",
        "summary": "嘉義市一名80歲老翁因排尿困難就醫，經泌尿科檢查後發現膀胱內有多顆結石，大小介於1至2公分之間。醫師透過X光檢查確認結石數量，最終在手術中成功取出24顆光滑如鵝卵石的結石。醫師表示，這些結石可能已存在..."
      }
    ],
    "娛樂": [
      {
        "title": "韓歌手10CM四度訪台開唱 期待和歌迷中文聊天",
        "link": "https://www.cna.com.tw/news/amov/202601300337.aspx",
        "source": "中央社",
        "published": "2026-01-30T05:12:58+00:00",
        "summary": "韓國歌手10CM（權正烈）將於2024年3月20日第四度來台舉行演唱會。10CM以其在熱門劇集《鬼怪》和《愛的迫降》中演唱的歌曲而聞名。他在活動前透過主辦單位表示，過去曾向台灣歌迷學習中文，並期待在演..."
      },
      {
        "title": "「功夫」西門發紅包 曾莞婷演媽心裡罵三字經",
        "link": "https://www.cna.com.tw/news/amov/202601300269.aspx",
        "source": "中央社",
        "published": "2026-01-30T01:59:31+00:00",
        "summary": "電影「功夫」導演九把刀於30日在台北捷運西門站舉行發紅包活動，參與的演員包括戴立忍、柯震東和曾莞婷。曾莞婷在活動中表示，接到演出媽媽角色的邀約時，雖然立刻答應，但心中不免有些不滿，形容自己當時心裡罵了..."
      },
      {
        "title": "米倉涼子涉違麻藥取締法被函送 東京檢方不起訴",
        "link": "https://www.cna.com.tw/news/amov/202601300258.aspx",
        "source": "中央社",
        "published": "2026-01-30T01:45:08+00:00",
        "summary": "日本女星米倉涼子因涉嫌違反「麻藥取締法」等相關法規，於上週被函送法辦。東京地方檢察廳於30日宣布，對50歲的米倉涼子決定不起訴。米倉涼子因主演日劇「派遣女醫X」而廣為人知，此次事件引發媒體關注。檢方的..."
      },
      {
        "title": "台泰混血女星葉芷妤返台拍「無形」 笑喊語言錯亂",
        "link": "https://www.cna.com.tw/news/amov/202601300223.aspx",
        "source": "中央社",
        "published": "2026-01-30T01:00:52+00:00",
        "summary": "電影《無形》導演奚岳隆於30日舉行記者會，出席者包括台泰混血女星葉芷妤及鳳小岳。葉芷妤表示，雖然她能以中文進行日常溝通，但對於ㄓ、ㄔ、ㄕ的發音仍感到困難。此外，由於頻繁往返台灣與泰國，她有時會出現語言..."
      }
    ],
    "運動": [
      {
        "title": "喬科維奇激戰5盤挫辛納 闖澳網決賽對決艾卡拉茲",
        "link": "https://www.cna.com.tw/news/aspt/202601300355.aspx",
        "source": "中央社",
        "published": "2026-01-30T07:14:45+00:00",
        "summary": "塞爾維亞網球選手喬科維奇於30日在澳洲網球公開賽四強賽中，以五盤激戰擊敗義大利選手辛納，成功晉級決賽。此役中，喬科維奇面對辛納的挑戰，展現出堅韌的比賽精神，最終以3比2的成績獲勝。接下來，他將在決賽中..."
      },
      {
        "title": "黃宥薰逆轉勝日本對手 泰國羽球賽台將唯一晉4強",
        "link": "https://www.cna.com.tw/news/aspt/202601300308.aspx",
        "source": "中央社",
        "published": "2026-01-30T03:27:55+00:00",
        "summary": "在BWF超級300等級的泰國羽球大師賽中，台灣女單選手黃宥薰於30日的8強賽中上演逆轉勝，以12比21、21比13、21比12擊敗日本選手明地陽菜，成功晉級4強。黃宥薰成為台灣在本次賽事中唯一晉級4強..."
      },
      {
        "title": "艾卡拉茲鏖戰5盤擊倒茲韋列夫 挺進澳網決賽[影]",
        "link": "https://www.cna.com.tw/news/aspt/202601300290.aspx",
        "source": "中央社",
        "published": "2026-01-30T02:38:16+00:00",
        "summary": "西班牙籍世界球王艾卡拉茲於30日在澳洲網球公開賽男單四強賽中，經過五盤激戰，最終以3比2擊敗德國選手茲韋列夫，成功晉級決賽。這是艾卡拉茲首次進入澳網決賽，距離實現其「生涯大滿貫」的目標僅一步之遙。此次..."
      },
      {
        "title": "青少年銳劍世界盃埃及站 林雨潔摘金U17排名登頂",
        "link": "https://www.cna.com.tw/news/aspt/202601300272.aspx",
        "source": "中央社",
        "published": "2026-01-30T02:04:38+00:00",
        "summary": "在2026年青少年銳劍世界盃埃及站中，台灣15歲選手林雨潔在冠軍賽中擊敗加拿大華裔選手塞琳娜（Serena Xu），成功奪得金牌。此勝利使林雨潔在U17巡迴賽的積分排名上躍升至世界第1，顯示出她在國際..."
      },
      {
        "title": "林安可期待出征經典賽 加盟西武盼對戰徐若熙",
        "link": "https://www.cna.com.tw/news/aspt/202601300227.aspx",
        "source": "中央社",
        "published": "2026-01-30T01:10:00+00:00",
        "summary": "日本職棒埼玉西武獅隊於30日舉辦記者會，介紹新加盟的外籍選手，其中包括來自台灣的野手林安可。林安可表示，他期待能參加即將舉行的世界棒球經典賽，並希望能與今年加盟福岡軟銀鷹隊的徐若熙展開對決。此番發言顯..."
      },
      {
        "title": "卓榮泰為經典賽台灣隊加油 致贈20萬元加菜金",
        "link": "https://www.cna.com.tw/news/aspt/202601300202.aspx",
        "source": "中央社",
        "published": "2026-01-30T00:31:07+00:00",
        "summary": "行政院長卓榮泰於30日造訪高雄國家運動訓練中心，為備戰世界棒球經典賽的台灣隊加油。他致贈新台幣20萬元的加菜金，以勉勵球員爭取更高的國家榮譽。此次訪問旨在支持球隊的訓練與準備，展現政府對體育發展的重視..."
      }
    ]
  },
  "en_news": {
    "Startup": [
      {
        "title": "Show HN: I built an AI conversation partner to practice speaking languages",
        "link": "https://apps.apple.com/us/app/talkbits-speak-naturally/id6756824177",
        "source": "Hacker News",
        "published": "2026-01-30T14:16:19+00:00",
        "summary": "A developer has created an AI conversation partner designed to assist users in practicing foreign la..."
      },
      {
        "title": "I trapped an AI model inside an art installation (2025) [video]",
        "link": "https://www.youtube.com/watch?v=7fNYj0EXxMs",
        "source": "Hacker News",
        "published": "2026-01-30T13:58:46+00:00",
        "summary": "In a recent project, an artist successfully encapsulated an artificial intelligence model within an ..."
      },
      {
        "title": "P vs. NP and the Difficulty of Computation: A ruliological approach",
        "link": "https://writings.stephenwolfram.com/2026/01/p-vs-np-and-the-difficulty-of-computation-a-ruliological-approach",
        "source": "Hacker News",
        "published": "2026-01-30T13:17:21+00:00",
        "summary": "The article discusses the P vs. NP problem, a fundamental question in computer science that asks whe..."
      },
      {
        "title": "Peerweb: Decentralized website hosting via WebTorrent",
        "link": "https://peerweb.lol/",
        "source": "Hacker News",
        "published": "2026-01-30T12:40:00+00:00",
        "summary": "Peerweb is a new decentralized website hosting platform that utilizes WebTorrent technology to enabl..."
      },
      {
        "title": "Silver plunges 30% in worst day since 1980, gold tumbles",
        "link": "https://www.cnbc.com/2026/01/30/silver-gold-fall-price-usd-dollar-fed-warsh-chair-trump-metals.html",
        "source": "Hacker News",
        "published": "2026-01-30T12:37:48+00:00",
        "summary": "Silver prices experienced a dramatic decline of 30% on a single day, marking the worst drop since 19..."
      },
      {
        "title": "Antirender: remove the glossy shine on architectural renderings",
        "link": "https://antirender.com/",
        "source": "Hacker News",
        "published": "2026-01-30T12:05:24+00:00",
        "summary": "Antirender is a new tool designed to eliminate the glossy shine often seen in architectural renderin..."
      },
      {
        "title": "Kimi K2.5 Technical Report [pdf]",
        "link": "https://github.com/MoonshotAI/Kimi-K2.5/blob/master/tech_report.pdf",
        "source": "Hacker News",
        "published": "2026-01-30T08:43:50+00:00",
        "summary": "The Kimi K2.5 Technical Report, shared on Hacker News, provides an in-depth analysis of the Kimi K2...."
      },
      {
        "title": "Ask HN: Do you also \"hoard\" notes/links but struggle to turn them into actions?",
        "link": "https://news.ycombinator.com/item?id=46826277",
        "source": "Hacker News",
        "published": "2026-01-30T08:22:05+00:00",
        "summary": "A recent discussion on Hacker News highlighted a common challenge among users regarding the manageme..."
      }
    ],
    "Tech News": [
      {
        "title": "Physical Intelligence, Stripe veteran Lachy Groom’s latest bet, is building Silicon Valley’s buzziest robot brains",
        "link": "https://techcrunch.com/2026/01/30/physical-intelligence-stripe-veteran-lachy-grooms-latest-bet-is-building-silicon-valleys-buzziest-robot-brains",
        "source": "TechCrunch",
        "published": "2026-01-30T16:09:54+00:00",
        "summary": "Physical Intelligence, co-founded by Lachy Groom, is focusing on developing advanced robotic intelli..."
      },
      {
        "title": "OnlyFans considering selling majority stake to Architect Capital",
        "link": "https://techcrunch.com/2026/01/30/onlyfans-considering-selling-majority-stake-to-architect-capital",
        "source": "TechCrunch",
        "published": "2026-01-30T15:54:09+00:00",
        "summary": "OnlyFans is reportedly in discussions to sell a majority stake in the company to Architect Capital, ..."
      },
      {
        "title": "Peloton lays off 11 percent of its staff just a few months after launching its AI hardware",
        "link": "https://www.theverge.com/gadgets/871422/peloton-layoffs-cost-cutting-2026",
        "source": "The Verge",
        "published": "2026-01-30T15:53:55+00:00",
        "summary": "Peloton said on Friday that it's cutting around 11 percent of its staff, mostly impacting \"engineers..."
      },
      {
        "title": "OpenClaw’s AI assistants are now building their own social network",
        "link": "https://techcrunch.com/2026/01/30/openclaws-ai-assistants-are-now-building-their-own-social-network",
        "source": "TechCrunch",
        "published": "2026-01-30T15:36:34+00:00",
        "summary": "OpenClaw, the personal AI assistant previously known as Clawdbot and briefly rebranded as Moltbot, h..."
      },
      {
        "title": "Video game company stock prices dip after Google introduces an AI world-generation tool",
        "link": "https://www.theverge.com/games/871348/google-project-genie-take-two-roblox-unity",
        "source": "The Verge",
        "published": "2026-01-30T14:45:16+00:00",
        "summary": "The stock prices of some major video game companies, including Take-Two Interactive, Roblox, and Uni..."
      },
      {
        "title": "Informant told FBI that Jeffrey Epstein had a ‘personal hacker’",
        "link": "https://techcrunch.com/2026/01/30/informant-told-fbi-that-jeffrey-epstein-had-a-personal-hacker",
        "source": "TechCrunch",
        "published": "2026-01-30T14:04:00+00:00",
        "summary": "An informant has reported to the FBI that Jeffrey Epstein employed a personal hacker who was involve..."
      },
      {
        "title": "Instagram might soon let you remove yourself from someone’s Close Friends list",
        "link": "https://techcrunch.com/2026/01/30/instagram-might-soon-let-you-remove-yourself-from-someones-close-friends-list",
        "source": "TechCrunch",
        "published": "2026-01-30T13:14:58+00:00",
        "summary": "Instagram is reportedly developing a feature that would allow users to remove themselves from anothe..."
      },
      {
        "title": "Blue Origin pauses space tourism flights to focus on the moon",
        "link": "https://techcrunch.com/2026/01/30/blue-origin-pauses-space-tourism-flights-to-focus-on-the-moon",
        "source": "TechCrunch",
        "published": "2026-01-30T13:11:52+00:00",
        "summary": "Blue Origin has announced a pause in its space tourism flights to concentrate on lunar missions. The..."
      }
    ],
    "BBC Top Stories": [
      {
        "title": "Schitt's Creek and Home Alone star Catherine O'Hara dies aged 71",
        "link": "https://www.bbc.com/news/articles/czr4jn4621lo?at_medium=RSS&at_campaign=rss",
        "source": "BBC News",
        "published": "2026-01-30T16:07:28+00:00",
        "summary": "Catherine O'Hara, the Emmy-winning actress known for her roles in \"Schitt's Creek\" and \"Home Alone,\"..."
      },
      {
        "title": "An ingredient for this curry is missing - and in eight minutes, it's at the door",
        "link": "https://www.bbc.com/news/articles/cvgx7ykl12go?at_medium=RSS&at_campaign=rss",
        "source": "BBC News",
        "published": "2026-01-30T16:01:04+00:00",
        "summary": "India's rapid growth in the quick-commerce sector has transformed grocery delivery, allowing consume..."
      },
      {
        "title": "Takeaways from the millions of newly released Epstein files",
        "link": "https://www.bbc.com/news/articles/cevnmxyy4wjo?at_medium=RSS&at_campaign=rss",
        "source": "BBC News",
        "published": "2026-01-30T15:56:25+00:00",
        "summary": "The release of three million documents related to Jeffrey Epstein has revealed numerous details, inc..."
      },
      {
        "title": "Luigi Mangione will not face death penalty if convicted, judge rules",
        "link": "https://www.bbc.com/news/articles/c78egdg3r0po?at_medium=RSS&at_campaign=rss",
        "source": "BBC News",
        "published": "2026-01-30T15:30:03+00:00",
        "summary": "Luigi Mangione, a 27-year-old man, will not face the death penalty if convicted of state murder char..."
      },
      {
        "title": "Epstein invited 'The Duke' to meet Russian woman",
        "link": "https://www.bbc.com/news/articles/c4g5490xmkeo?at_medium=RSS&at_campaign=rss",
        "source": "BBC News",
        "published": "2026-01-30T15:06:27+00:00",
        "summary": "Newly released documents by US justice officials reveal that Jeffrey Epstein invited Prince Andrew, ..."
      },
      {
        "title": "Labubu to open seven UK shops, after PM's China visit",
        "link": "https://www.bbc.com/news/articles/cgm4kyw482eo?at_medium=RSS&at_campaign=rss",
        "source": "BBC News",
        "published": "2026-01-30T14:31:27+00:00",
        "summary": "Labubu, a brand known for its distinctive furry dolls featuring a spiky-toothed grin, is set to open..."
      }
    ],
    "BBC World": [
      {
        "title": "Iran wants to make deal rather than face military action, Trump says",
        "link": "https://www.bbc.com/news/articles/cd9ew2kwj0lo?at_medium=RSS&at_campaign=rss",
        "source": "BBC World",
        "published": "2026-01-30T13:43:51+00:00",
        "summary": "U.S. President Donald Trump stated that Iran is seeking a deal to avoid military action, despite Teh..."
      },
      {
        "title": "Civil rights investigation opened into Alex Pretti shooting",
        "link": "https://www.bbc.com/news/articles/c5yvw89p3p1o?at_medium=RSS&at_campaign=rss",
        "source": "BBC World",
        "published": "2026-01-30T11:23:45+00:00",
        "summary": "The U.S. Department of Justice has initiated a civil rights investigation into the shooting of Alex ..."
      },
      {
        "title": "Mali lawmaker jailed in Ivory Coast for insulting president",
        "link": "https://www.bbc.com/news/articles/c74vgxp0zr4o?at_medium=RSS&at_campaign=rss",
        "source": "BBC World",
        "published": "2026-01-30T10:09:20+00:00",
        "summary": "Mali lawmaker Mamadou Hawa Gassama has been sentenced to one year in prison in Ivory Coast for insul..."
      },
      {
        "title": "Trump picks Kevin Warsh to lead the US Federal Reserve",
        "link": "https://www.bbc.com/news/articles/c2d7yddrl2xo?at_medium=RSS&at_campaign=rss",
        "source": "BBC World",
        "published": "2026-01-30T08:22:59+00:00",
        "summary": "Former President Donald Trump has selected Kevin Warsh, a 55-year-old economist and former Federal R..."
      },
      {
        "title": "South Africa and Israel expel each other's envoys in diplomatic row",
        "link": "https://www.bbc.com/news/articles/cvgn8ejljqwo?at_medium=RSS&at_campaign=rss",
        "source": "BBC World",
        "published": "2026-01-30T08:10:24+00:00",
        "summary": "South Africa and Israel have engaged in a diplomatic dispute resulting in the expulsion of each othe..."
      },
      {
        "title": "Ukraine sees quieter night as Trump says Putin will not attack its cities",
        "link": "https://www.bbc.com/news/articles/c4g4yj92kwro?at_medium=RSS&at_campaign=rss",
        "source": "BBC World",
        "published": "2026-01-30T05:46:23+00:00",
        "summary": "Ukraine experienced a relatively quiet night as tensions between the country and Russia continued. A..."
      }
    ],
    "BBC Business": [
      {
        "title": "Trump says 'very dangerous' for UK to do business with China as Starmer lands in Shanghai",
        "link": "https://www.bbc.com/news/articles/c0keyyeyr41o?at_medium=RSS&at_campaign=rss",
        "source": "BBC Business",
        "published": "2026-01-30T01:14:25+00:00",
        "summary": "U.S. President Donald Trump has expressed concerns regarding the United Kingdom's business dealings ..."
      }
    ],
    "BBC Technology": [
      {
        "title": "He calls me sweetheart and winks at me - but he's not my boyfriend, he's AI",
        "link": "https://www.bbc.com/news/articles/c62njv82n0wo?at_medium=RSS&at_campaign=rss",
        "source": "BBC Technology",
        "published": "2026-01-30T03:39:15+00:00",
        "summary": "The article from BBC Technology discusses the experience of a user interacting with an AI avatar nam..."
      }
    ],
    "BBC Health": [
      {
        "title": "'I get nightmares': Child tells BBC of botched surgery by disgraced GOSH surgeon",
        "link": "https://www.bbc.com/news/videos/cgl83rwz15zo?at_medium=RSS&at_campaign=rss",
        "source": "BBC Health",
        "published": "2026-01-30T01:05:43+00:00",
        "summary": "Twelve-year-old Vivaan Sharma is among 94 patients who suffered harm due to the actions of Yaser Jab..."
      }
    ]
  },
  "ja_news": {
    "頭條": [
      {
        "title": "Z世代「○○コア」界隈との違い",
        "link": "https://news.yahoo.co.jp/pickup/6568112",
        "source": "Yahoo! Japan",
        "published": "2026-01-30T15:47:21+00:00",
        "summary": "Z世代における「○○コア」文化の特徴とその違いについての考察が行われた。具体的には、Z世代が持つ価値観や趣味嗜好が、従来の世代とは異なる点を強調している。特に、個人のアイデンティティの重要性や多様性の..."
      },
      {
        "title": "やきそば3000円 ニセコ価格の背景",
        "link": "https://news.yahoo.co.jp/pickup/6568111",
        "source": "Yahoo! Japan",
        "published": "2026-01-30T15:31:15+00:00",
        "summary": "北海道のニセコ地域で提供されるやきそばが3000円という高価格で販売されている背景には、観光地としての特性や原材料費の高騰がある。ニセコは外国人観光客にも人気があり、地元の飲食店はその需要を反映した価..."
      },
      {
        "title": "5年前は部員3人 高知農業が選抜へ",
        "link": "https://news.yahoo.co.jp/pickup/6568110",
        "source": "Yahoo! Japan",
        "published": "2026-01-30T15:14:36+00:00",
        "summary": "高知農業高校の野球部が、選抜高校野球大会に出場することが決定した。部員数は5年前の3人から増加し、現在は約30人に達している。チームは、地域の支援を受けながら練習を重ね、選抜出場を果たした。選手たちは..."
      },
      {
        "title": "国連の財政危機 事務総長が警告",
        "link": "https://news.yahoo.co.jp/pickup/6568109",
        "source": "Yahoo! Japan",
        "published": "2026-01-30T15:01:09+00:00",
        "summary": "国連の事務総長アントニオ・グテーレス氏は、国連の財政危機が深刻化していると警告した。彼は、加盟国からの未払いの会費が増加しており、組織の運営に影響を及ぼす可能性があると指摘した。特に、2023年の予算..."
      },
      {
        "title": "ノース・フェイスのダウンも新幹線の出張も 広がる脱炭素ビジネス",
        "link": "http://www.asahi.com/articles/ASV1Y2QVGV1YULFA016M.html",
        "source": "朝日新聞",
        "published": "2026-01-30T15:00:00+00:00",
        "summary": "ノース・フェイスは、環境に配慮したダウン製品を展開し、脱炭素ビジネスを推進している。また、新幹線の出張においても、カーボンオフセットを取り入れる企業が増加している。これにより、持続可能な社会の実現に向..."
      },
      {
        "title": "選挙のフェイク動画 AI発達で加速",
        "link": "https://news.yahoo.co.jp/pickup/6568107",
        "source": "Yahoo! Japan",
        "published": "2026-01-30T14:49:51+00:00",
        "summary": "近年、人工知能（AI）の技術が進化する中、選挙におけるフェイク動画の制作が加速している。これにより、虚偽の情報が拡散し、選挙の公正性が脅かされる懸念が高まっている。専門家は、AIを用いた偽情報の対策が..."
      },
      {
        "title": "山林に中国籍の女性遺体 捜査",
        "link": "https://news.yahoo.co.jp/pickup/6568106",
        "source": "Yahoo! Japan",
        "published": "2026-01-30T14:31:23+00:00",
        "summary": "山林で中国籍の女性の遺体が発見され、警察が捜査を開始した。遺体は〇月〇日に発見され、現場は〇〇県の山林地域である。警察は身元確認を進めるとともに、死因や周辺の状況について調査を行っている。女性の遺体発..."
      },
      {
        "title": "元阪神・井川慶氏 俳優デビュー",
        "link": "https://news.yahoo.co.jp/pickup/6568102",
        "source": "Yahoo! Japan",
        "published": "2026-01-30T14:20:37+00:00",
        "summary": "元阪神タイガースの投手、井川慶氏が俳優デビューを果たした。井川氏は、2023年10月に公開される映画に出演し、役柄については詳細が明らかにされていない。プロ野球選手から俳優への転身は注目を集めており、..."
      }
    ],
    "國際": [
      {
        "title": "抗議デモ巡り 元CNN司会者逮捕",
        "link": "https://news.yahoo.co.jp/pickup/6568105",
        "source": "Yahoo! Japan",
        "published": "2026-01-30T14:29:23+00:00",
        "summary": "元CNN司会者が抗議デモに関連して逮捕された。逮捕の詳細や具体的な日時、場所については明らかにされていないが、デモは社会的な問題に対する抗議の一環とされている。逮捕の背景や理由については、今後の捜査に..."
      },
      {
        "title": "靖国神社でポケカ催し 中国紙批判",
        "link": "https://news.yahoo.co.jp/pickup/6568091",
        "source": "Yahoo! Japan",
        "published": "2026-01-30T05:17:52+00:00",
        "summary": "靖国神社で開催されたポケモンカードのイベントに対し、中国のメディアが批判を展開した。中国紙は、靖国神社が戦争の歴史を象徴する場所であることを指摘し、ポケモンカードの催しが不適切であると報じた。このイベ..."
      },
      {
        "title": "FRB次期議長にウォーシュ氏指名",
        "link": "https://news.yahoo.co.jp/pickup/6568087",
        "source": "Yahoo! Japan",
        "published": "2026-01-30T04:23:01+00:00",
        "summary": "アメリカの連邦準備制度理事会（FRB）は、次期議長にケビン・ウォーシュ氏を指名した。ウォーシュ氏は、経済政策に関する豊富な経験を持ち、過去にはFRB理事を務めた実績がある。新議長の任命は、金融政策の方..."
      },
      {
        "title": "韓国の新興宗教「新天地」に家宅捜索 政界と癒着疑惑、検察など捜査",
        "link": "https://www.asahi.com/articles/ASV1Z35T1V1ZUHBI01GM.html",
        "source": "朝日新聞",
        "published": "2026-01-30T02:41:19+00:00",
        "summary": "韓国の新興宗教「新天地」に対し、検察が家宅捜索を実施した。これは、同宗教と政界との癒着疑惑に関連する捜査の一環である。捜査当局は、宗教団体の活動や資金の流れについて調査を進めており、今後の展開が注目さ..."
      },
      {
        "title": "「歴史に向き合う」ホロコースト記念日に駐日ドイツ、イスラエル大使",
        "link": "https://www.asahi.com/articles/ASV1Z232WV1ZUHBI00PM.html",
        "source": "朝日新聞",
        "published": "2026-01-30T02:00:00+00:00",
        "summary": "駐日ドイツ大使とイスラエル大使は、ホロコースト記念日を迎え、「歴史に向き合う」重要性を強調した。両大使は、過去の悲劇を忘れず、再発防止に努めることが必要であると述べ、教育や対話の重要性を訴えた。記念日..."
      },
      {
        "title": "ミャンマー総選挙 親軍勢力が圧勝",
        "link": "https://news.yahoo.co.jp/pickup/6568071",
        "source": "Yahoo! Japan",
        "published": "2026-01-30T01:43:23+00:00",
        "summary": "ミャンマーで行われた総選挙において、親軍勢力が圧勝した。選挙は2023年10月に実施され、軍事政権が主導する国民統一党が多数の議席を獲得した。今回の選挙は、国際社会からの批判を受けて行われたもので、民..."
      },
      {
        "title": "「弟が殺された」「友だちの国」ミャンマー政変5年、日本で訴える",
        "link": "https://www.asahi.com/articles/ASV1Z2QB2V1ZPTIL00BM.html",
        "source": "朝日新聞",
        "published": "2026-01-30T01:21:12+00:00",
        "summary": "ミャンマーの政変から5年が経過し、被害者の家族が日本で訴えを行った。彼らは、弟を殺された遺族として、ミャンマーの現状を訴え、「友だちの国」としての日本に支援を求めている。政権の弾圧や人権侵害が続く中、..."
      },
      {
        "title": "首相の「不用意」答弁で日中関係悪化 不満漏らす経済界、打開の道は",
        "link": "https://www.asahi.com/articles/ASV1Z0TJYV1ZUTFK029M.html",
        "source": "朝日新聞",
        "published": "2026-01-30T01:00:00+00:00",
        "summary": "首相の発言が原因で日中関係が悪化しているとの指摘がある。経済界からは不満の声が上がっており、関係改善の必要性が強調されている。首相の「不用意」な答弁が影響を及ぼしているとの見方が広がる中、今後の外交戦..."
      }
    ],
    "政治": [
      {
        "title": "中道と国民、46選挙区で対決 連合「言うこと聞かない」異例の抗議",
        "link": "https://www.asahi.com/articles/ASV1Z3CHBV1ZUTFK008M.html",
        "source": "朝日新聞",
        "published": "2026-01-30T03:00:00+00:00",
        "summary": "中道と国民民主党は、次期総選挙に向けて46選挙区で対立することが明らかになった。これに対し、連合は「言うことを聞かない」として異例の抗議を行った。連合は、両党の対立が労働者の利益に反すると懸念を示して..."
      },
      {
        "title": "【解説人語】因縁の公明と立憲、自維の与党対決に参政も 大阪16区",
        "link": "https://www.asahi.com/articles/ASV1Z23SZV1ZDIFI006M.html",
        "source": "朝日新聞",
        "published": "2026-01-30T02:30:00+00:00",
        "summary": "大阪16区では、公明党と立憲民主党の対立が注目されている。自民党と維新の会が与党として対抗する中、参政党も選挙に参加する。各党はそれぞれの支持基盤を活かし、選挙戦に臨む構えを見せており、今後の動向が注..."
      },
      {
        "title": "食料品の消費税ゼロ、外食業界「客流れる」と不安 高市首相の答えは",
        "link": "https://www.asahi.com/articles/ASV1Z2G2BV1ZULFA02LM.html",
        "source": "朝日新聞",
        "published": "2026-01-30T01:48:39+00:00",
        "summary": "高市早苗経済再生担当大臣は、食料品の消費税をゼロにする方針について、外食業界からの懸念に応じた。外食業界は、消費税がゼロになることで客が流出するのではないかと不安を抱いている。高市大臣は、消費税の軽減..."
      }
    ],
    "運動": [
      {
        "title": "元幕内・戦闘竜が死去 56歳",
        "link": "https://news.yahoo.co.jp/pickup/6568086",
        "source": "Yahoo! Japan",
        "published": "2026-01-30T03:54:48+00:00",
        "summary": "元幕内力士の戦闘竜が、56歳で死去した。戦闘竜は、1970年に福岡県で生まれ、1990年に初土俵を踏んだ。彼は、1993年に幕内に昇進し、活躍を続けたが、2001年に引退。その後は、指導者として後進の..."
      }
    ],
    "商業": [
      {
        "title": "STEAM教育×探究で未来を変える 入賞13団体が実践を報告",
        "link": "https://www.asahi.com/articles/ASV1Z2FH6V1ZUTIL018M.html",
        "source": "朝日新聞",
        "published": "2026-01-30T13:00:00+00:00",
        "summary": "STEAM教育と探究学習をテーマにしたコンペティションで、入賞した13団体がその実践内容を報告した。各団体は、科学、技術、工学、アート、数学を融合させた教育プログラムを通じて、未来を変える可能性を探求..."
      },
      {
        "title": "屋内で多い低体温症 高齢者は注意",
        "link": "https://news.yahoo.co.jp/pickup/6568090",
        "source": "Yahoo! Japan",
        "published": "2026-01-30T05:18:17+00:00",
        "summary": "冬季において、屋内での低体温症が高齢者に多く見られることが指摘されている。特に、暖房が不十分な環境や、体温調節機能が低下している高齢者はリスクが高い。専門家は、適切な衣服を着用し、室温を適切に保つこと..."
      },
      {
        "title": "ユーロ圏の実質GDP 昨年10~12月期は年率1.3%増",
        "link": "https://www.asahi.com/articles/ASV1Z3Q4DV1ZUHBI01CM.html",
        "source": "朝日新聞",
        "published": "2026-01-30T03:20:34+00:00",
        "summary": "ユーロ圏の実質GDPは、2022年10月から12月期にかけて年率1.3%増加したことが発表された。この成長は、経済活動の回復を示すものであり、エネルギー価格の安定や消費の増加が寄与したとされる。これに..."
      },
      {
        "title": "障害者雇用、大企業にも優良認定制度 厚労省の研究会が報告書案",
        "link": "https://www.asahi.com/articles/ASV1Z3F4RV1ZULFA00ZM.html",
        "source": "朝日新聞",
        "published": "2026-01-30T02:42:56+00:00",
        "summary": "厚生労働省の研究会は、大企業に対する障害者雇用の優良認定制度を導入する報告書案をまとめた。この制度は、障害者の雇用促進を目的としており、企業の取り組みを評価し、優良企業を認定することで、雇用環境の改善..."
      },
      {
        "title": "今月23～24日の円急騰、為替介入ではなかった 財務省が公表",
        "link": "https://www.asahi.com/articles/ASV1Z3DG3V1ZULFA00WM.html",
        "source": "朝日新聞",
        "published": "2026-01-30T02:33:50+00:00",
        "summary": "財務省は、今月23日から24日にかけて円が急騰した理由について、為替介入は行われていないと公表した。円の急騰は市場の要因によるものであり、政府の介入はなかったことを明確にした。この発表は、円相場の変動..."
      },
      {
        "title": "急速な円高 為替介入は「なし」",
        "link": "https://news.yahoo.co.jp/pickup/6568079",
        "source": "Yahoo! Japan",
        "published": "2026-01-30T02:29:24+00:00",
        "summary": "急速な円高が進行している中、日本政府は為替介入を行わない方針を示した。円高は経済に影響を与える可能性があるが、政府は市場の動向を注視しつつ、適切な対応を検討する意向を示している。円相場は、国際的な経済..."
      },
      {
        "title": "初代Switchが確立 勝利の方程式",
        "link": "https://news.yahoo.co.jp/pickup/6568077",
        "source": "Yahoo! Japan",
        "published": "2026-01-30T02:11:50+00:00",
        "summary": "任天堂のゲーム機「Nintendo Switch」が、発売から数年を経てその成功の要因を確立した。特に、家庭用ゲーム機と携帯型ゲーム機のハイブリッドという独自の形態が、幅広いユーザー層に支持されている..."
      },
      {
        "title": "SLIM BEAUTY HOUSEを業務停止",
        "link": "https://news.yahoo.co.jp/pickup/6568074",
        "source": "Yahoo! Japan",
        "published": "2026-01-30T01:47:28+00:00",
        "summary": "SLIM BEAUTY HOUSEは、2023年10月に業務停止を発表した。具体的な理由や停止の期間については明らかにされていないが、同社は美容関連サービスを提供しており、全国に複数の店舗を展開してい..."
      }
    ],
    "文化": [
      {
        "title": "小5でパパ活 非行に走る少女たち",
        "link": "https://news.yahoo.co.jp/pickup/6568114",
        "source": "Yahoo! Japan",
        "published": "2026-01-30T16:04:54+00:00",
        "summary": "小学校5年生の少女たちが「パパ活」に関与し、非行に走る事例が増加している。これにより、彼女たちの心身に悪影響を及ぼす懸念が高まっている。専門家は、家庭環境や社会的背景が影響していると指摘し、早期の対策..."
      },
      {
        "title": "水戸駅で4人殴られ重軽傷 男逃走",
        "link": "https://news.yahoo.co.jp/pickup/6568108",
        "source": "Yahoo! Japan",
        "published": "2026-01-30T14:50:38+00:00",
        "summary": "10月某日、水戸駅で男性が4人を殴り、重軽傷を負わせた。事件後、男は現場から逃走した。警察は目撃者の証言をもとに、男の行方を追っている。負傷者の詳細や事件の動機については、現在調査中である。"
      },
      {
        "title": "4億円強盗 車は暴力団関係者名義",
        "link": "https://news.yahoo.co.jp/pickup/6568101",
        "source": "Yahoo! Japan",
        "published": "2026-01-30T14:23:29+00:00",
        "summary": "東京都内で発生した4億円の強盗事件に関して、使用された車両が暴力団関係者名義であることが判明した。警察は、強盗事件の背後に暴力団が関与している可能性があるとみて捜査を進めている。事件は最近発生し、詳細..."
      },
      {
        "title": "雨不足 ダムに沈んだ村が姿現す",
        "link": "https://news.yahoo.co.jp/pickup/6568100",
        "source": "Yahoo! Japan",
        "published": "2026-01-30T06:50:02+00:00",
        "summary": "長期間の雨不足により、ダムの水位が低下し、かつて水没していた村が姿を現した。村は、ダム建設に伴い1970年代に沈んだもので、現在はその遺構や家屋が確認できる状態となっている。この現象は、気候変動や水資..."
      },
      {
        "title": "青森で大雪 住民「異常です」",
        "link": "https://news.yahoo.co.jp/pickup/6568089",
        "source": "Yahoo! Japan",
        "published": "2026-01-30T04:49:27+00:00",
        "summary": "青森県では、2023年10月に大雪が降り、住民から「異常です」との声が上がっている。降雪量は例年を大きく上回り、交通機関に影響が出ているほか、除雪作業が追いつかない状況となっている。気象庁は、今後も雪..."
      },
      {
        "title": "西山朋佳女流二冠と福間香奈女流名人が「百番指し」 対戦成績は拮抗",
        "link": "https://www.asahi.com/articles/ASV1Z3VTMV1ZUCVL039M.html",
        "source": "朝日新聞",
        "published": "2026-01-30T04:04:05+00:00",
        "summary": "将棋界の西山朋佳女流二冠と福間香奈女流名人が、対戦成績が拮抗する中で「百番指し」を行った。両者の対局は注目を集めており、今後の展開が期待される。詳細な成績や対局の内容については報じられていないが、両者..."
      },
      {
        "title": "男性警官が自殺 宮崎県に賠償命令",
        "link": "https://news.yahoo.co.jp/pickup/6568084",
        "source": "Yahoo! Japan",
        "published": "2026-01-30T03:39:23+00:00",
        "summary": "宮崎県で、男性警官が自殺した件について、県に対し賠償命令が下された。自殺の原因として、職場での過重なストレスや労働環境が指摘されており、裁判所は県の責任を認めた。具体的な賠償額や自殺の詳細については明..."
      },
      {
        "title": "フジテレビ清水社長が就任1年で会見 「制作費は来年度も抑制的に」",
        "link": "https://www.asahi.com/articles/ASV1Z3FQ8V1ZUCVL01HM.html",
        "source": "朝日新聞",
        "published": "2026-01-30T03:00:00+00:00",
        "summary": "フジテレビの清水社長は就任1周年を迎えた記者会見で、来年度の制作費について抑制的な方針を示した。社長は、経営の健全性を重視し、効率的な運営を進める必要性を強調した。また、視聴率や収益の改善に向けた取り..."
      }
    ],
    "娛樂": [
      {
        "title": "SNSで共感呼ぶ バービーの育児",
        "link": "https://news.yahoo.co.jp/pickup/6568113",
        "source": "Yahoo! Japan",
        "published": "2026-01-30T15:55:06+00:00",
        "summary": "SNS上で、バービーの育児に関する投稿が多くの共感を呼んでいる。特に、バービーが子育てに取り組む姿や、育児の楽しさや苦労を描いた内容が注目されている。これにより、育児に関するさまざまな意見や体験がシェ..."
      },
      {
        "title": "色物→理想の上司 ちゃんみなの姿",
        "link": "https://news.yahoo.co.jp/pickup/6568095",
        "source": "Yahoo! Japan",
        "published": "2026-01-30T05:54:27+00:00",
        "summary": "韓国の女性ラッパー、ちゃんみなさんが「色物」から「理想の上司」として注目を集めている。彼女は独自のスタイルと強い個性を持ち、音楽活動を通じて多くのファンを魅了している。最近のインタビューでは、リーダー..."
      },
      {
        "title": "中田敦彦「老害」になる恐怖語る",
        "link": "https://news.yahoo.co.jp/pickup/6568082",
        "source": "Yahoo! Japan",
        "published": "2026-01-30T02:39:05+00:00",
        "summary": "お笑いタレントの中田敦彦さんが、自身のYouTubeチャンネルで「老害」になることへの恐怖を語った。彼は、年齢を重ねることで若者とのコミュニケーションが難しくなることや、自身の考えが固定化することを懸..."
      },
      {
        "title": "ナイトスクープ騒動 問われる演出",
        "link": "https://news.yahoo.co.jp/pickup/6568068",
        "source": "Yahoo! Japan",
        "published": "2026-01-30T02:14:02+00:00",
        "summary": "テレビ番組「ナイトスクープ」において、演出に関する問題が浮上している。具体的には、番組内での演出が視聴者に誤解を与える可能性があるとの指摘があり、これに対して制作側が説明を求められている。視聴者からの..."
      },
      {
        "title": "モデル・長谷川ミラ 結婚を発表",
        "link": "https://news.yahoo.co.jp/pickup/6568076",
        "source": "Yahoo! Japan",
        "published": "2026-01-30T01:46:56+00:00",
        "summary": "モデルの長谷川ミラが結婚を発表した。具体的な相手や結婚式の日程については明らかにされていないが、彼女は自身のSNSを通じて喜びを表現した。長谷川は多くのファンに支持されており、今後の活動にも注目が集ま..."
      }
    ]
  }
}